tensorflow_serving/__init__.py
tensorflow_serving/apis/__init__.py
tensorflow_serving/apis/classification_pb2.py
tensorflow_serving/apis/get_model_metadata_pb2.py
tensorflow_serving/apis/get_model_status_pb2.py
tensorflow_serving/apis/inference_pb2.py
tensorflow_serving/apis/input_pb2.py
tensorflow_serving/apis/logging_pb2.py
tensorflow_serving/apis/model_management_pb2.py
tensorflow_serving/apis/model_pb2.py
tensorflow_serving/apis/model_service_pb2.py
tensorflow_serving/apis/model_service_pb2_grpc.py
tensorflow_serving/apis/predict_pb2.py
tensorflow_serving/apis/prediction_log_pb2.py
tensorflow_serving/apis/prediction_service_pb2.py
tensorflow_serving/apis/prediction_service_pb2_grpc.py
tensorflow_serving/apis/regression_pb2.py
tensorflow_serving/apis/session_service_pb2.py
tensorflow_serving/apis/status_pb2.py
tensorflow_serving/config/__init__.py
tensorflow_serving/config/file_system_storage_path_source_pb2.py
tensorflow_serving/config/log_collector_config_pb2.py
tensorflow_serving/config/logging_config_pb2.py
tensorflow_serving/config/model_server_config_pb2.py
tensorflow_serving_api-2.19.1.dist-info/METADATA
tensorflow_serving_api-2.19.1.dist-info/WHEEL
tensorflow_serving_api-2.19.1.dist-info/top_level.txt
tensorflow_serving_api-2.19.1.dist-info/RECORD
